[
    {
        "stock_code": "8495",
        "type": "Ordinary shares",
        "issuer": "1957 & Co. (Hospitality) Limited",
        "first_date": "2017-12-05",
        "total_return": "-52.73"
    },
    {
        "stock_code": "3601",
        "type": "Ordinary shares",
        "issuer": "360 LUDASHI HOLDINGS LIMITED",
        "first_date": "2019-10-10",
        "total_return": "-68.26"
    },
    {
        "stock_code": "1361",
        "type": "Ordinary shares",
        "issuer": "361 Degrees International Limited",
        "first_date": "2009-06-30",
        "total_return": "-44.84"
    },
    {
        "stock_code": "1530",
        "type": "Ordinary shares",
        "issuer": "3SBio Inc.",
        "first_date": "2015-06-11",
        "total_return": "-14.41"
    },
    {
        "stock_code": "2051",
        "type": "Ordinary shares",
        "issuer": "51 Credit Card Inc.",
        "first_date": "2018-07-13",
        "total_return": "-90.00"
    },
    {
        "stock_code": "0797",
        "type": "Ordinary shares",
        "issuer": "7Road Holdings Limited",
        "first_date": "2018-07-18",
        "total_return": "94.22"
    },
    {
        "stock_code": "1737",
        "type": "Ordinary shares",
        "issuer": "A & S Group (Holdings) Limited",
        "first_date": "2018-03-14",
        "total_return": "-80.94"
    },
    {
        "stock_code": "3319",
        "type": "PRC ordinary shares listed in HK",
        "issuer": "A-Living Services Co., Ltd.",
        "first_date": "2018-02-09",
        "total_return": "254.06"
    },
    {
        "stock_code": "1841",
        "type": "Ordinary shares",
        "issuer": "A.Plus Group Holdings Limited",
        "first_date": "2019-01-11",
        "total_return": "-30.54"
    },
    {
        "stock_code": "0800",
        "type": "Ordinary shares",
        "issuer": "A8 New Media Group Limited",
        "first_date": "2008-06-12",
        "total_return": "-91.99"
    },
    {
        "stock_code": "2018",
        "type": "Ordinary shares",
        "issuer": "AAC TECHNOLOGIES HOLDINGS INC.",
        "first_date": "2005-08-09",
        "total_return": "1,778.71"
    },
    {
        "stock_code": "2686",
        "type": "Ordinary shares",
        "issuer": "AAG Energy Holdings Limited",
        "first_date": "2015-06-23",
        "total_return": "-49.31"
    },
    {
        "stock_code": "1615",
        "type": "Ordinary shares",
        "issuer": "AB Builders Group Limited",
        "first_date": "2018-09-10",
        "total_return": "-59.06"
    },
    {
        "stock_code": "8131",
        "type": "Ordinary shares",
        "issuer": "ABC MULTIACTIVE LIMITED",
        "first_date": "2001-01-31",
        "total_return": "-97.17"
    },
    {
        "stock_code": "1627",
        "type": "Ordinary shares",
        "issuer": "Able Engineering Holdings Limited",
        "first_date": "2017-02-20",
        "total_return": "-54.75"
    },
    {
        "stock_code": "1283",
        "type": "Ordinary shares",
        "issuer": "Accel Group Holdings Limited",
        "first_date": "2019-10-18",
        "total_return": "-18.92"
    },
    {
        "stock_code": "1870",
        "type": "Ordinary shares",
        "issuer": "Acme International Holdings Limited",
        "first_date": "2019-11-08",
        "total_return": "-67.61"
    },
    {
        "stock_code": "9919",
        "type": "Ordinary shares",
        "issuer": "Activation Group Holdings Limited (KY)",
        "first_date": "2020-01-16",
        "total_return": "-56.69"
    },
    {
        "stock_code": "2623",
        "type": "Ordinary shares",
        "issuer": "Add New Energy Investment Holdings Group Limited",
        "first_date": "2012-04-27",
        "total_return": "-84.54"
    },
    {
        "stock_code": "0900",
        "type": "Ordinary shares",
        "issuer": "AEON CREDIT SERVICE (ASIA) COMPANY LIMITED",
        "first_date": "1995-09-14",
        "total_return": "1,299.87"
    },
    {
        "stock_code": "0984",
        "type": "Ordinary shares",
        "issuer": "AEON STORES (HONG KONG) CO., LIMITED",
        "first_date": "1994-02-04",
        "total_return": "343.74"
    },
    {
        "stock_code": "8341",
        "type": "Ordinary shares",
        "issuer": "Aeso Holding Limited",
        "first_date": "2017-01-13",
        "total_return": "-95.53"
    },
    {
        "stock_code": "1757",
        "type": "Ordinary shares",
        "issuer": "Affluent Foundation Holdings Limited",
        "first_date": "2018-06-07",
        "total_return": "-48.89"
    },
    {
        "stock_code": "1466",
        "type": "Ordinary shares",
        "issuer": "Affluent Partners Holdings Limited",
        "first_date": "2014-10-17",
        "total_return": "-69.87"
    },
    {
        "stock_code": "3383",
        "type": "Ordinary shares",
        "issuer": "Agile Group Holdings Limited",
        "first_date": "2005-12-15",
        "total_return": "473.80"
    },
    {
        "stock_code": "1288",
        "type": "PRC ordinary shares listed in HK",
        "issuer": "AGRICULTURAL BANK OF CHINA LIMITED",
        "first_date": "2010-07-16",
        "total_return": "54.12"
    },
    {
        "stock_code": "1131",
        "type": "Ordinary shares",
        "issuer": "Agritrade Resources Limited",
        "first_date": "1997-03-19",
        "total_return": "-66.05"
    },
    {
        "stock_code": "8279",
        "type": "Ordinary shares",
        "issuer": "AGTech Holdings Limited",
        "first_date": "2004-01-19",
        "total_return": "409.62"
    },
    {
        "stock_code": "8290",
        "type": "Ordinary shares",
        "issuer": "Ahsay Backup Software Development Company Limited",
        "first_date": "2015-10-08",
        "total_return": "-99.27"
    },
    {
        "stock_code": "1299",
        "type": "Ordinary shares",
        "issuer": "AIA Group Limited",
        "first_date": "2010-10-29",
        "total_return": "234.12"
    },
    {
        "stock_code": "8088",
        "type": "Ordinary shares",
        "issuer": "AID Life Science Holdings Limited",
        "first_date": "2000-04-17",
        "total_return": "-99.96"
    },
    {
        "stock_code": "0286",
        "type": "Ordinary shares",
        "issuer": "Aidigong Maternal & Child Health Limited (BM)",
        "first_date": "1990-09-07",
        "total_return": "-100.00"
    },
    {
        "stock_code": "0753",
        "type": "PRC ordinary shares listed in HK",
        "issuer": "Air China Limited",
        "first_date": "2004-12-15",
        "total_return": "137.12"
    },
    {
        "stock_code": "0538",
        "type": "Ordinary shares",
        "issuer": "Ajisen (China) Holdings Limited",
        "first_date": "2007-03-30",
        "total_return": "-61.14"
    },
    {
        "stock_code": "1789",
        "type": "Ordinary shares",
        "issuer": "AK Medical Holdings Limited",
        "first_date": "2017-12-20",
        "total_return": "524.61"
    },
    {
        "stock_code": "1639",
        "type": "Ordinary shares",
        "issuer": "AKM INDUSTRIAL COMPANY LIMITED",
        "first_date": "2014-06-18",
        "total_return": "-20.78"
    },
    {
        "stock_code": "8360",
        "type": "Ordinary shares",
        "issuer": "AL Group Limited",
        "first_date": "2016-07-12",
        "total_return": "-91.43"
    },
    {
        "stock_code": "0328",
        "type": "Ordinary shares",
        "issuer": "ALCO HOLDINGS LIMITED (BM)",
        "first_date": "1992-11-27",
        "total_return": "-10.15"
    },
    {
        "stock_code": "9988",
        "type": "Ordinary shares",
        "issuer": "Alibaba Group Holding Limited (KY)",
        "first_date": "2019-11-26",
        "total_return": "0.64"
    },
    {
        "stock_code": "0241",
        "type": "Ordinary shares",
        "issuer": "Alibaba Health Information Technology Limited",
        "first_date": "1971-06-30",
        "total_return": "3,039.34"
    },
    {
        "stock_code": "1060",
        "type": "Ordinary shares",
        "issuer": "Alibaba Pictures Group Limited",
        "first_date": "1994-05-12",
        "total_return": "-96.91"
    },
    {
        "stock_code": "0684",
        "type": "Ordinary shares",
        "issuer": "ALLAN INTERNATIONAL HOLDINGS LIMITED",
        "first_date": "1992-11-10",
        "total_return": "464.86"
    },
    {
        "stock_code": "0373",
        "type": "Ordinary shares",
        "issuer": "ALLIED GROUP LIMITED (HK)",
        "first_date": "1987-03-02",
        "total_return": "457.73"
    },
    {
        "stock_code": "0056",
        "type": "Ordinary shares",
        "issuer": "ALLIED PROPERTIES (H.K.) LIMITED",
        "first_date": "1981-01-08",
        "total_return": "15.69"
    },
    {
        "stock_code": "8320",
        "type": "Ordinary shares",
        "issuer": "Allied Sustainability and Environmental Consultants Group Limited",
        "first_date": "2016-10-17",
        "total_return": "-94.89"
    },
    {
        "stock_code": "0833",
        "type": "Ordinary shares",
        "issuer": "ALLTRONICS HOLDINGS LIMITED",
        "first_date": "2005-07-15",
        "total_return": "91.05"
    },
    {
        "stock_code": "8406",
        "type": "Ordinary shares",
        "issuer": "Alpha Era International Holdings Limited",
        "first_date": "2017-12-07",
        "total_return": "-68.36"
    },
    {
        "stock_code": "0948",
        "type": "Ordinary shares",
        "issuer": "Alpha Professional Holdings Limited",
        "first_date": "2010-03-01",
        "total_return": "-95.22"
    },
    {
        "stock_code": "9966",
        "type": "Ordinary shares",
        "issuer": "Alphamab Oncology",
        "first_date": "2019-12-12",
        "total_return": "6.07"
    },
    {
        "stock_code": "8149",
        "type": "Ordinary shares",
        "issuer": "Altus Holdings Limited (KY)",
        "first_date": "2016-10-17",
        "total_return": "-94.98"
    },
    {
        "stock_code": "2600",
        "type": "PRC ordinary shares listed in HK",
        "issuer": "ALUMINUM CORPORATION OF CHINA LIMITED",
        "first_date": "2001-12-12",
        "total_return": "59.33"
    },
    {
        "stock_code": "1849",
        "type": "Ordinary shares",
        "issuer": "AM Group Holdings Limited",
        "first_date": "2019-06-26",
        "total_return": "-65.71"
    },
    {
        "stock_code": "8168",
        "type": "Ordinary shares",
        "issuer": "Amasse Capital Holdings Limited",
        "first_date": "2018-03-22",
        "total_return": "-66.81"
    },
    {
        "stock_code": "0630",
        "type": "Ordinary shares",
        "issuer": "AMCO United Holding Limited",
        "first_date": "1996-11-28",
        "total_return": "-99.84"
    },
    {
        "stock_code": "0077",
        "type": "Ordinary shares",
        "issuer": "AMS PUBLIC TRANSPORT HOLDINGS LIMITED",
        "first_date": "2004-04-15",
        "total_return": "127.87"
    },
    {
        "stock_code": "8545",
        "type": "Ordinary shares",
        "issuer": "Amuse Group Holding Limited",
        "first_date": "2018-05-31",
        "total_return": "-80.50"
    },
    {
        "stock_code": "2300",
        "type": "Ordinary shares",
        "issuer": "AMVIG Holdings Limited",
        "first_date": "2004-03-26",
        "total_return": "139.48"
    },
    {
        "stock_code": "8353",
        "type": "Ordinary shares",
        "issuer": "ANACLE SYSTEMS LIMITED",
        "first_date": "2016-12-16",
        "total_return": "-58.33"
    },
    {
        "stock_code": "1977",
        "type": "Ordinary shares",
        "issuer": "ANALOGUE HOLDINGS LIMITED",
        "first_date": "2019-07-12",
        "total_return": "-31.78"
    },
    {
        "stock_code": "1592",
        "type": "Ordinary shares",
        "issuer": "Anchorstone Holdings Limited",
        "first_date": "2018-07-04",
        "total_return": "48.15"
    },
    {
        "stock_code": "0347",
        "type": "PRC ordinary shares listed in HK",
        "issuer": "Angang Steel Company Limited",
        "first_date": "1997-07-24",
        "total_return": "276.67"
    },
    {
        "stock_code": "0914",
        "type": "PRC ordinary shares listed in HK",
        "issuer": "Anhui Conch Cement Company Limited",
        "first_date": "1997-10-21",
        "total_return": "14,790.01"
    },
    {
        "stock_code": "0995",
        "type": "PRC ordinary shares listed in HK",
        "issuer": "ANHUI EXPRESSWAY COMPANY LIMITED",
        "first_date": "1996-11-13",
        "total_return": "623.37"
    },
    {
        "stock_code": "2020",
        "type": "Ordinary shares",
        "issuer": "ANTA Sports Products Limited",
        "first_date": "2007-07-10",
        "total_return": "1,193.96"
    },
    {
        "stock_code": "3337",
        "type": "Ordinary shares",
        "issuer": "Anton Oilfield Services Group",
        "first_date": "2007-12-14",
        "total_return": "-60.80"
    },
    {
        "stock_code": "0922",
        "type": "Ordinary shares",
        "issuer": "Anxian Yuan China Holdings Limited",
        "first_date": "1999-12-21",
        "total_return": "-99.84"
    },
    {
        "stock_code": "1370",
        "type": "Ordinary shares",
        "issuer": "Aowei Holding Limited",
        "first_date": "2013-11-28",
        "total_return": "-48.05"
    },
    {
        "stock_code": "3662",
        "type": "Ordinary shares",
        "issuer": "Aoyuan Healthy Life Group Company Limited",
        "first_date": "2019-03-18",
        "total_return": "60.77"
    },
    {
        "stock_code": "1496",
        "type": "Ordinary shares",
        "issuer": "AP Rentals Holdings Limited",
        "first_date": "2016-04-08",
        "total_return": "-81.80"
    },
    {
        "stock_code": "1104",
        "type": "Ordinary shares",
        "issuer": "APAC Resources Limited",
        "first_date": "1998-12-29",
        "total_return": "-68.08"
    },
    {
        "stock_code": "6036",
        "type": "Ordinary shares",
        "issuer": "Apex Ace Holding Limited",
        "first_date": "2018-03-16",
        "total_return": "-85.10"
    },
    {
        "stock_code": "0519",
        "type": "Ordinary shares",
        "issuer": "Applied Development Holdings Limited",
        "first_date": "1989-01-10",
        "total_return": "-92.60"
    },
    {
        "stock_code": "1045",
        "type": "Ordinary shares",
        "issuer": "APT SATELLITE HOLDINGS LIMITED",
        "first_date": "1996-12-18",
        "total_return": "-24.67"
    },
    {
        "stock_code": "0645",
        "type": "Ordinary shares",
        "issuer": "Ares Asia Limited",
        "first_date": "1993-12-22",
        "total_return": "-77.35"
    },
    {
        "stock_code": "0565",
        "type": "Ordinary shares",
        "issuer": "Art Group Holdings Limited (KY)",
        "first_date": "2003-09-10",
        "total_return": "-34.29"
    },
    {
        "stock_code": "3313",
        "type": "Ordinary shares",
        "issuer": "ArtGo Holdings Limited",
        "first_date": "2013-12-30",
        "total_return": "-93.85"
    },
    {
        "stock_code": "0789",
        "type": "Ordinary shares",
        "issuer": "Artini Holdings Limited",
        "first_date": "2008-05-16",
        "total_return": "-97.92"
    },
    {
        "stock_code": "1120",
        "type": "Ordinary shares",
        "issuer": "ARTS OPTICAL INTERNATIONAL HOLDINGS LIMITED",
        "first_date": "1996-11-08",
        "total_return": "150.34"
    },
    {
        "stock_code": "6855",
        "type": "Ordinary shares",
        "issuer": "Ascentage Pharma Group International",
        "first_date": "2019-10-28",
        "total_return": "-25.40"
    },
    {
        "stock_code": "1672",
        "type": "Ordinary shares",
        "issuer": "Ascletis Pharma Inc.",
        "first_date": "2018-08-01",
        "total_return": "-76.07"
    },
    {
        "stock_code": "0711",
        "type": "Ordinary shares",
        "issuer": "ASIA ALLIED INFRASTRUCTURE HOLDINGS LIMITED",
        "first_date": "1993-02-12",
        "total_return": "189.93"
    },
    {
        "stock_code": "0841",
        "type": "Ordinary shares",
        "issuer": "Asia Cassava Resources Holdings Limited",
        "first_date": "2009-03-23",
        "total_return": "-69.62"
    },
    {
        "stock_code": "0743",
        "type": "Ordinary shares",
        "issuer": "Asia Cement (China) Holdings Corporation",
        "first_date": "2008-05-20",
        "total_return": "106.98"
    },
    {
        "stock_code": "0104",
        "type": "Ordinary shares",
        "issuer": "ASIA COMMERCIAL HOLDINGS LIMITED",
        "first_date": "1987-07-29",
        "total_return": "-98.27"
    },
    {
        "stock_code": "0351",
        "type": "Ordinary shares",
        "issuer": "ASIA ENERGY LOGISTICS GROUP LIMITED",
        "first_date": "1992-08-18",
        "total_return": "-99.89"
    },
    {
        "stock_code": "0662",
        "type": "Ordinary shares",
        "issuer": "ASIA FINANCIAL HOLDINGS LIMITED",
        "first_date": "1990-12-18",
        "total_return": "162.57"
    },
    {
        "stock_code": "8413",
        "type": "Ordinary shares",
        "issuer": "Asia Grocery Distribution Limited",
        "first_date": "2017-04-13",
        "total_return": "27.50"
    },
    {
        "stock_code": "0214",
        "type": "Ordinary shares",
        "issuer": "ASIA ORIENT HOLDINGS LIMITED",
        "first_date": "1986-01-06",
        "total_return": "-82.12"
    },
    {
        "stock_code": "0767",
        "type": "Ordinary shares",
        "issuer": "Asia Pacific Silk Road Investment Company Limited",
        "first_date": "1995-11-20",
        "total_return": "-99.97"
    },
    {
        "stock_code": "8400",
        "type": "Ordinary shares",
        "issuer": "Asia Pioneer Entertainment Holdings Limited",
        "first_date": "2017-11-15",
        "total_return": "-78.06"
    },
    {
        "stock_code": "0899",
        "type": "Ordinary shares",
        "issuer": "ASIA RESOURCES HOLDINGS LIMITED",
        "first_date": "1997-10-24",
        "total_return": "-99.99"
    },
    {
        "stock_code": "0292",
        "type": "Ordinary shares",
        "issuer": "ASIA STANDARD HOTEL GROUP LIMITED",
        "first_date": "1988-09-22",
        "total_return": "-99.71"
    },
    {
        "stock_code": "0129",
        "type": "Ordinary shares",
        "issuer": "ASIA STANDARD INTERNATIONAL GROUP LIMITED",
        "first_date": "1973-01-24",
        "total_return": "-75.81"
    },
    {
        "stock_code": "0679",
        "type": "Ordinary shares",
        "issuer": "ASIA TELE-NET AND TECHNOLOGY CORPORATION LIMITED",
        "first_date": "1991-01-31",
        "total_return": "64.77"
    },
    {
        "stock_code": "0707",
        "type": "Ordinary shares",
        "issuer": "Asia Television Holdings Limited",
        "first_date": "2006-03-30",
        "total_return": "-95.70"
    },
    {
        "stock_code": "8193",
        "type": "Ordinary shares",
        "issuer": "Asia-Pac Financial Investment Company Limited",
        "first_date": "2011-05-31",
        "total_return": "-96.80"
    },
    {
        "stock_code": "1675",
        "type": "Ordinary shares",
        "issuer": "AsiaInfo Technologies Limited",
        "first_date": "2018-12-19",
        "total_return": "-7.19"
    },
    {
        "stock_code": "8025",
        "type": "Ordinary shares",
        "issuer": "Asian Capital Resources (Holdings) Limited",
        "first_date": "1999-12-16",
        "total_return": "-91.61"
    },
    {
        "stock_code": "0073",
        "type": "Ordinary shares",
        "issuer": "ASIAN CITRUS HOLDINGS LIMITED",
        "first_date": "2009-11-26",
        "total_return": "-96.55"
    },
    {
        "stock_code": "1993",
        "type": "Ordinary shares",
        "issuer": "Asiaray Media Group Limited",
        "first_date": "2015-01-15",
        "total_return": "29.82"
    }
]